odoo/addons/geoengine_swisstopo/README.rst
odoo/addons/geoengine_swisstopo/__init__.py
odoo/addons/geoengine_swisstopo/__manifest__.py
odoo/addons/geoengine_swisstopo/geo_view/__init__.py
odoo/addons/geoengine_swisstopo/geo_view/geo_raster_layer.py
odoo/addons/geoengine_swisstopo/geo_view/geo_raster_layer_view.xml
odoo/addons/geoengine_swisstopo/i18n/geoengine_swisstopo.pot
odoo/addons/geoengine_swisstopo/static/description/icon.png
odoo/addons/geoengine_swisstopo/static/lib/proj4-src.js
odoo/addons/geoengine_swisstopo/static/lib/proj4.js
odoo/addons/geoengine_swisstopo/static/src/js/.eslintrc
odoo/addons/geoengine_swisstopo/static/src/js/geoengine_swisstopo.js
odoo/addons/geoengine_swisstopo/views/geoengine_swisstopo_view.xml
odoo12_addon_geoengine_swisstopo-12.0.1.1.0.dist-info/METADATA
odoo12_addon_geoengine_swisstopo-12.0.1.1.0.dist-info/WHEEL
odoo12_addon_geoengine_swisstopo-12.0.1.1.0.dist-info/top_level.txt
odoo12_addon_geoengine_swisstopo-12.0.1.1.0.dist-info/RECORD
